{
  "start_date": "2025-01-01",
  "end_date": "2025-11-09",
  "trading_pair": "XRP-USDT",
  "backtest_resolution": "15m",
  "plot_frequency": "3min",
  "environment": "prod",
  "trading_fees": {
    "maker_fee": 0.0,
    "taker_fee": 0.0002,
    "maker_fee_pct": 0.0,
    "taker_fee_pct": 0.02,
    "maker_fee_wan": 0.0,
    "taker_fee_wan": 2.0
  },
  "data_info": {
    "trading_pair": "XRP-USDT",
    "data_points": 29184,
    "actual_start": "2025-01-01 08:00:00",
    "actual_end": "2025-11-01 07:45:00",
    "backtest_resolution": "15m"
  },
  "results": [
    {
      "trading_pair": "XRP-USDT",
      "strategy_key": "PMM_Simple",
      "strategy_name": "PMM Simple",
      "success": true,
      "elapsed_time": 1274.8224740028381,
      "total_executors": 57079,
      "filled_executors": 2614,
      "fill_rate": 0.04579617722805235,
      "buy_orders": 28553,
      "sell_orders": 28526,
      "buy_filled": 1300,
      "sell_filled": 1314,
      "buy_fill_rate": 0.04552936644135468,
      "sell_fill_rate": 0.04606324055247844,
      "total_pnl": 3258.6645385394017,
      "total_volume": 13072991.435207177,
      "turnover_return": 0.02492669374634039,
      "return_pct": 32.58664538539402,
      "buy_pnl": 4065.657135945749,
      "sell_pnl": -806.9925974063473,
      "total_orders": 57079,
      "cancelled_orders": 54465,
      "daily_volume": 41900.613574381976,
      "daily_pnl": 10.444437623523724,
      "daily_return": 2.4926693746340387,
      "max_position_value": 5853.192883320026,
      "max_long_position_value": 4999.996509844681,
      "max_short_position_value": 5853.192883320026,
      "maker_fee_paid": 0.0,
      "taker_fee_paid": 2614.5982870414355
    },
    {
      "trading_pair": "XRP-USDT",
      "strategy_key": "PMM_Dynamic",
      "strategy_name": "PMM Dynamic (MACD)",
      "success": true,
      "elapsed_time": 1406.6943860054016,
      "total_executors": 43830,
      "filled_executors": 29107,
      "fill_rate": 0.6640885238421173,
      "buy_orders": 24366,
      "sell_orders": 19464,
      "buy_filled": 9643,
      "sell_filled": 19464,
      "buy_fill_rate": 0.3957563818435525,
      "sell_fill_rate": 1.0,
      "total_pnl": -51575.54602841763,
      "total_volume": 145468915.8427199,
      "turnover_return": -0.03545468509862326,
      "return_pct": -515.7554602841764,
      "buy_pnl": -9525.635202767826,
      "sell_pnl": -42049.9108256498,
      "total_orders": 43830,
      "cancelled_orders": 14723,
      "daily_volume": 466246.5251369228,
      "daily_pnl": -165.3062372705693,
      "daily_return": -3.545468509862326,
      "max_position_value": 5003.660531583093,
      "max_long_position_value": 4999.999033133658,
      "max_short_position_value": 5003.660531583093,
      "maker_fee_paid": 0.0,
      "taker_fee_paid": 29093.783168543985
    },
    {
      "trading_pair": "XRP-USDT",
      "strategy_key": "PMM_Bar_Portion",
      "strategy_name": "PMM Bar Portion",
      "success": true,
      "elapsed_time": 1062.9263889789581,
      "total_executors": 46673,
      "filled_executors": 23339,
      "fill_rate": 0.5000535641591498,
      "buy_orders": 23328,
      "sell_orders": 23345,
      "buy_filled": 11720,
      "sell_filled": 11619,
      "buy_fill_rate": 0.502400548696845,
      "sell_fill_rate": 0.49770828871278644,
      "total_pnl": -33919.17927509977,
      "total_volume": 116696018.86805195,
      "turnover_return": -0.029066269444420506,
      "return_pct": -339.1917927509977,
      "buy_pnl": -15564.71215979273,
      "sell_pnl": -18354.467115307038,
      "total_orders": 46673,
      "cancelled_orders": 23334,
      "daily_volume": 374025.7015001665,
      "daily_pnl": -108.71531818942233,
      "daily_return": -2.90662694444205,
      "max_position_value": 5882.25538733125,
      "max_long_position_value": 4999.999694028869,
      "max_short_position_value": 5882.25538733125,
      "maker_fee_paid": 0.0,
      "taker_fee_paid": 23339.203773610392
    }
  ],
  "total_time": 2454.152529001236
}